README.rst
setup.py
netticapy/__init__.py
netticapy/api.py
netticapy.egg-info/PKG-INFO
netticapy.egg-info/SOURCES.txt
netticapy.egg-info/dependency_links.txt
netticapy.egg-info/not-zip-safe
netticapy.egg-info/requires.txt
netticapy.egg-info/top_level.txt