Metadata-Version: 1.1
Name: netticapy
Version: 1.1
Summary: A nettica.com API wrapper.
Home-page: https://bitbucket.org/fabian/netticapy
Author: Fabian Topfstedt
Author-email: topfstedt@schneevonmorgen.com
License: UNKNOWN
Platform: UNKNOWN
Classifier: Development Status :: 4 - Beta
Classifier: Environment :: Web Environment
Classifier: Intended Audience :: Developers
Classifier: License :: OSI Approved :: MIT License
Classifier: Operating System :: OS Independent
Classifier: Programming Language :: Python
